corprep/__cli__.py
corprep/__init__.py
corprep/_version.py
corprep/conf/__init__.py
corprep/conf/about/corprep.yaml
corprep/conf/agent/corprep-gpt3.yaml
corprep/conf/agent/corprep-gpt4.yaml
corprep/conf/prompts/corprep.yaml
corprep/conf/runner/corprep-gpt3.yaml
corprep/conf/runner/corprep-gpt4.yaml
corprep/datasets/__init__.py
corprep/py.typed
corporate_reputation-0.18.0.dist-info/LICENSE
corporate_reputation-0.18.0.dist-info/METADATA
corporate_reputation-0.18.0.dist-info/WHEEL
corporate_reputation-0.18.0.dist-info/entry_points.txt
corporate_reputation-0.18.0.dist-info/RECORD
