Metadata-Version: 2.1
Name: corporate-reputation
Version: 0.18.0
Summary: Unraveling Corporate and CEO Reputation using Aspect-Based Sentiment Analysis and Signal Modeling
Home-page: https://entelecheia.github.io/corporate-reputation
License: MIT
Author: Young Joon Lee
Author-email: entelecheia@hotmail.com
Requires-Python: >=3.9,<3.13
Classifier: License :: OSI Approved :: MIT License
Classifier: Programming Language :: Python :: 3
Classifier: Programming Language :: Python :: 3.9
Classifier: Programming Language :: Python :: 3.10
Classifier: Programming Language :: Python :: 3.11
Classifier: Programming Language :: Python :: 3.12
Requires-Dist: hyfi (>=1.36.3,<2.0.0)
Requires-Dist: hyfi-absa (>=0.5.0,<0.6.0)
Requires-Dist: lexikanon (>=0.6.4,<0.7.0)
Requires-Dist: thematos (>=0.14.4,<0.15.0)
Project-URL: Repository, https://github.com/entelecheia/corporate-reputation
